{"v":"4.7.1","fr":60,"ip":0,"op":669,"w":1920,"h":1080,"nm":"Comp 2","ddd":0,"assets":[{"id":"comp_0","layers":[{"ddd":0,"ind":1,"ty":4,"nm":"Shape Layer 19","ks":{"o":{"a":0,"k":100},"r":{"a":0,"k":0},"p":{"a":0,"k":[0,1080,0]},"a":{"a":0,"k":[-960,270,0]},"s":{"a":0,"k":[100,100,100]}},"ao":0,"shapes":[{"ty":"gr","it":[{"ind":0,"ty":"sh","ix":1,"ks":{"a":1,"k":[{"i":{"x":0,"y":1},"o":{"x":0.816,"y":0},"n":"0_1_0p816_0","t":550,"s":[{"i":[[258.487,0],[361,0],[0,0],[0,0],[0,0],[0,0],[0,0]],"o":[[-361,0],[-361,0],[0,0],[0,0],[0,0],[0,0],[-123.761,0]],"v":[[694.754,-518.586],[-27.108,-518.648],[-568.746,-518.648],[-568.746,20.289],[1343.707,20.289],[1351.254,20.289],[1351.254,-518.586]],"c":true}],"e":[{"i":[[258.487,0],[361,0],[0,0],[0,0],[0,0],[0,0],[0,0]],"o":[[-361,0],[-361,0],[0,0],[0,0],[0,0],[0,0],[-123.761,0]],"v":[[694.754,-159.711],[-27.108,-519.711],[-568.746,-519.711],[-568.746,20.289],[1343.707,20.289],[1351.254,20.289],[1351.254,-159.711]],"c":true}]},{"t":634}]},"nm":"Path 1","mn":"ADBE Vector Shape - Group"},{"ty":"fl","c":{"a":0,"k":[0,0.9411765,0.7058824,1]},"o":{"a":0,"k":100},"r":1,"nm":"Fill 1","mn":"ADBE Vector Graphic - Fill"},{"ty":"tr","p":{"a":0,"k":[-391.254,249.711],"ix":2},"a":{"a":0,"k":[0,0],"ix":1},"s":{"a":0,"k":[100,100],"ix":3},"r":{"a":0,"k":0,"ix":6},"o":{"a":0,"k":100,"ix":7},"sk":{"a":0,"k":0,"ix":4},"sa":{"a":0,"k":0,"ix":5},"nm":"Transform"}],"nm":"Rectangle 1","np":3,"cix":2,"ix":1,"mn":"ADBE Vector Group"}],"ip":549,"op":656,"st":29,"bm":0,"sr":1},{"ddd":0,"ind":2,"ty":1,"nm":"Black Solid 3","td":1,"ks":{"o":{"a":0,"k":100},"r":{"a":0,"k":0},"p":{"a":0,"k":[960,1080,0]},"a":{"a":0,"k":[960,539,0]},"s":{"a":0,"k":[100,100,100]}},"ao":0,"sw":1920,"sh":539,"sc":"#000000","ip":490,"op":549,"st":29,"bm":0,"sr":1},{"ddd":0,"ind":3,"ty":4,"nm":"Shape Layer 16","tt":1,"ks":{"o":{"a":0,"k":100},"r":{"a":0,"k":0},"p":{"a":0,"k":[0,90.789,0]},"a":{"a":0,"k":[-315.408,-449.211,0]},"s":{"a":0,"k":[100,100,100]}},"ao":0,"shapes":[{"ty":"gr","it":[{"ind":0,"ty":"sh","ix":1,"ks":{"a":1,"k":[{"i":{"x":0.667,"y":1},"o":{"x":0.333,"y":0},"n":"0p667_1_0p333_0","t":501,"s":[{"i":[[0,0],[0,0],[0,0],[0,0]],"o":[[0,0],[0,0],[0,0],[0,0]],"v":[[-109.954,-91.289],[1812.204,-91.289],[1812.204,92.289],[-109.954,92.289]],"c":true}],"e":[{"i":[[0,0],[0,0],[0,0],[0,0]],"o":[[0,0],[0,0],[0,0],[0,0]],"v":[[-109.954,-91.289],[1812.204,-91.289],[1812.204,991.289],[-109.954,991.289]],"c":true}]},{"t":544}]},"nm":"Path 1","mn":"ADBE Vector Shape - Group"},{"ty":"fl","c":{"a":0,"k":[0,0.9411765,0.7058824,1]},"o":{"a":0,"k":100},"r":1,"nm":"Fill 1","mn":"ADBE Vector Graphic - Fill"},{"ty":"tr","p":{"a":0,"k":[-205.454,-449.211],"ix":2},"a":{"a":0,"k":[0,0],"ix":1},"s":{"a":0,"k":[100,100],"ix":3},"r":{"a":0,"k":0,"ix":6},"o":{"a":0,"k":100,"ix":7},"sk":{"a":0,"k":0,"ix":4},"sa":{"a":0,"k":0,"ix":5},"nm":"Transform"}],"nm":"Rectangle 1","np":3,"cix":2,"ix":1,"mn":"ADBE Vector Group"}],"ip":490,"op":549,"st":29,"bm":0,"sr":1},{"ddd":0,"ind":4,"ty":1,"nm":"Black Solid 2","td":1,"ks":{"o":{"a":0,"k":100},"r":{"a":0,"k":0},"p":{"a":0,"k":[960,1080,0]},"a":{"a":0,"k":[960,533,0]},"s":{"a":0,"k":[100,100,100]}},"ao":0,"sw":1920,"sh":533,"sc":"#000000","ip":490,"op":549,"st":29,"bm":0,"sr":1},{"ddd":0,"ind":5,"ty":4,"nm":"Shape Layer 13","tt":2,"ks":{"o":{"a":0,"k":100},"r":{"a":0,"k":0},"p":{"a":0,"k":[0,90.789,0]},"a":{"a":0,"k":[-315.408,-449.211,0]},"s":{"a":0,"k":[100,100,100]}},"ao":0,"shapes":[{"ty":"gr","it":[{"ind":0,"ty":"sh","ix":1,"ks":{"a":1,"k":[{"i":{"x":0,"y":1},"o":{"x":1,"y":0},"n":"0_1_1_0","t":501,"s":[{"i":[[0,0],[0,0],[0,0],[0,0]],"o":[[0,0],[0,0],[0,0],[0,0]],"v":[[-109.954,-91.289],[1812.204,-91.289],[1812.204,92.07],[-109.954,92.07]],"c":true}],"e":[{"i":[[0,0],[0,0],[0,0],[0,0]],"o":[[0,0],[0,0],[0,0],[0,0]],"v":[[-109.954,468.711],[1812.204,468.711],[1812.204,991.289],[-109.954,991.289]],"c":true}]},{"t":537}]},"nm":"Path 1","mn":"ADBE Vector Shape - Group"},{"ty":"fl","c":{"a":0,"k":[0.8823529,0.8941176,0.9019608,1]},"o":{"a":0,"k":100},"r":1,"nm":"Fill 1","mn":"ADBE Vector Graphic - Fill"},{"ty":"tr","p":{"a":0,"k":[-205.454,-449.211],"ix":2},"a":{"a":0,"k":[0,0],"ix":1},"s":{"a":0,"k":[100,100],"ix":3},"r":{"a":0,"k":0,"ix":6},"o":{"a":0,"k":100,"ix":7},"sk":{"a":0,"k":0,"ix":4},"sa":{"a":0,"k":0,"ix":5},"nm":"Transform"}],"nm":"Rectangle 1","np":3,"cix":2,"ix":1,"mn":"ADBE Vector Group"}],"ip":490,"op":549,"st":29,"bm":0,"sr":1},{"ddd":0,"ind":6,"ty":1,"nm":"Black Solid 2","td":1,"ks":{"o":{"a":0,"k":100},"r":{"a":0,"k":0},"p":{"a":0,"k":[960,1080,0]},"a":{"a":0,"k":[960,533,0]},"s":{"a":0,"k":[100,100,100]}},"ao":0,"sw":1920,"sh":533,"sc":"#000000","ip":490,"op":549,"st":29,"bm":0,"sr":1},{"ddd":0,"ind":7,"ty":4,"nm":"Shape Layer 15","tt":1,"ks":{"o":{"a":0,"k":67},"r":{"a":0,"k":0},"p":{"a":0,"k":[0,273.289,0]},"a":{"a":0,"k":[-315.408,-449.211,0]},"s":{"a":0,"k":[100,100,100]}},"ao":0,"shapes":[{"ty":"gr","it":[{"ind":0,"ty":"sh","ix":1,"ks":{"a":1,"k":[{"i":{"x":0,"y":1},"o":{"x":1,"y":0},"n":"0_1_1_0","t":501,"s":[{"i":[[0,0],[0,0],[0,0],[0,0]],"o":[[0,0],[0,0],[0,0],[0,0]],"v":[[-109.954,-91.289],[1812.204,-91.289],[1812.204,91.289],[-109.954,91.289]],"c":true}],"e":[{"i":[[0,0],[0,0],[0,0],[0,0]],"o":[[0,0],[0,0],[0,0],[0,0]],"v":[[-109.954,272.711],[1812.204,272.711],[1812.204,811.289],[-109.954,811.289]],"c":true}]},{"t":538}]},"nm":"Path 1","mn":"ADBE Vector Shape - Group"},{"ty":"fl","c":{"a":0,"k":[0,0.9411765,0.7058824,1]},"o":{"a":0,"k":100},"r":1,"nm":"Fill 1","mn":"ADBE Vector Graphic - Fill"},{"ty":"tr","p":{"a":0,"k":[-205.454,-449.211],"ix":2},"a":{"a":0,"k":[0,0],"ix":1},"s":{"a":0,"k":[100,100],"ix":3},"r":{"a":0,"k":0,"ix":6},"o":{"a":0,"k":100,"ix":7},"sk":{"a":0,"k":0,"ix":4},"sa":{"a":0,"k":0,"ix":5},"nm":"Transform"}],"nm":"Rectangle 1","np":3,"cix":2,"ix":1,"mn":"ADBE Vector Group"}],"ip":490,"op":549,"st":29,"bm":0,"sr":1},{"ddd":0,"ind":8,"ty":1,"nm":"Black Solid 2","td":1,"ks":{"o":{"a":0,"k":100},"r":{"a":0,"k":0},"p":{"a":0,"k":[960,1080,0]},"a":{"a":0,"k":[960,533,0]},"s":{"a":0,"k":[100,100,100]}},"ao":0,"sw":1920,"sh":533,"sc":"#000000","ip":490,"op":549,"st":29,"bm":0,"sr":1},{"ddd":0,"ind":9,"ty":4,"nm":"Shape Layer 12","tt":2,"ks":{"o":{"a":0,"k":100},"r":{"a":0,"k":0},"p":{"a":0,"k":[0,273.289,0]},"a":{"a":0,"k":[-315.408,-449.211,0]},"s":{"a":0,"k":[100,100,100]}},"ao":0,"shapes":[{"ty":"gr","it":[{"ind":0,"ty":"sh","ix":1,"ks":{"a":1,"k":[{"i":{"x":0,"y":1},"o":{"x":1,"y":0},"n":"0_1_1_0","t":501,"s":[{"i":[[0,0],[0,0],[0,0],[0,0]],"o":[[0,0],[0,0],[0,0],[0,0]],"v":[[-109.954,-91.289],[1812.204,-91.289],[1812.204,91.289],[-109.954,91.289]],"c":true}],"e":[{"i":[[0,0],[0,0],[0,0],[0,0]],"o":[[0,0],[0,0],[0,0],[0,0]],"v":[[-109.954,272.711],[1812.204,272.711],[1812.204,807.289],[-109.954,807.289]],"c":true}]},{"t":537}]},"nm":"Path 1","mn":"ADBE Vector Shape - Group"},{"ty":"fl","c":{"a":0,"k":[0.9490196,0.9568627,0.9686275,1]},"o":{"a":0,"k":100},"r":1,"nm":"Fill 1","mn":"ADBE Vector Graphic - Fill"},{"ty":"tr","p":{"a":0,"k":[-205.454,-449.211],"ix":2},"a":{"a":0,"k":[0,0],"ix":1},"s":{"a":0,"k":[100,100],"ix":3},"r":{"a":0,"k":0,"ix":6},"o":{"a":0,"k":100,"ix":7},"sk":{"a":0,"k":0,"ix":4},"sa":{"a":0,"k":0,"ix":5},"nm":"Transform"}],"nm":"Rectangle 1","np":3,"cix":2,"ix":1,"mn":"ADBE Vector Group"}],"ip":490,"op":549,"st":29,"bm":0,"sr":1},{"ddd":0,"ind":10,"ty":1,"nm":"Black Solid 2","td":1,"ks":{"o":{"a":0,"k":100},"r":{"a":0,"k":0},"p":{"a":0,"k":[960,1080,0]},"a":{"a":0,"k":[960,533,0]},"s":{"a":0,"k":[100,100,100]}},"ao":0,"sw":1920,"sh":533,"sc":"#000000","ip":490,"op":549,"st":29,"bm":0,"sr":1},{"ddd":0,"ind":11,"ty":4,"nm":"Shape Layer 14","tt":1,"ks":{"o":{"a":0,"k":33},"r":{"a":0,"k":0},"p":{"a":0,"k":[961.079,546.578,0]},"a":{"a":0,"k":[645.671,-357.922,0]},"s":{"a":0,"k":[100,100,100]}},"ao":0,"shapes":[{"ty":"gr","it":[{"ind":0,"ty":"sh","ix":1,"ks":{"a":1,"k":[{"i":{"x":0,"y":1},"o":{"x":1,"y":0},"n":"0_1_1_0","t":501,"s":[{"i":[[0,0],[0,0],[0,0],[0,0]],"o":[[0,0],[0,0],[0,0],[0,0]],"v":[[-109.954,-91.289],[1812.204,-91.289],[1812.204,90.859],[-109.954,90.977]],"c":true}],"e":[{"i":[[0,0],[0,0],[0,0],[0,0]],"o":[[0,0],[0,0],[0,0],[0,0]],"v":[[-109.954,90.961],[1812.204,90.961],[1812.204,649.539],[-109.954,649.539]],"c":true}]},{"t":519.80078125}]},"nm":"Path 1","mn":"ADBE Vector Shape - Group"},{"ty":"fl","c":{"a":0,"k":[0,0.9411765,0.7058824,1]},"o":{"a":0,"k":100},"r":1,"nm":"Fill 1","mn":"ADBE Vector Graphic - Fill"},{"ty":"tr","p":{"a":0,"k":[-205.454,-449.211],"ix":2},"a":{"a":0,"k":[0,0],"ix":1},"s":{"a":0,"k":[100,100],"ix":3},"r":{"a":0,"k":0,"ix":6},"o":{"a":0,"k":100,"ix":7},"sk":{"a":0,"k":0,"ix":4},"sa":{"a":0,"k":0,"ix":5},"nm":"Transform"}],"nm":"Rectangle 1","np":3,"cix":2,"ix":1,"mn":"ADBE Vector Group"}],"ip":490,"op":549,"st":29,"bm":0,"sr":1},{"ddd":0,"ind":12,"ty":1,"nm":"Black Solid 2","td":1,"ks":{"o":{"a":0,"k":100},"r":{"a":0,"k":0},"p":{"a":0,"k":[960,1080,0]},"a":{"a":0,"k":[960,533,0]},"s":{"a":0,"k":[100,100,100]}},"ao":0,"sw":1920,"sh":533,"sc":"#000000","ip":490,"op":549,"st":29,"bm":0,"sr":1},{"ddd":0,"ind":13,"ty":4,"nm":"Shape Layer 1","tt":2,"ks":{"o":{"a":0,"k":100},"r":{"a":0,"k":0},"p":{"a":0,"k":[961.079,546.578,0]},"a":{"a":0,"k":[645.671,-357.922,0]},"s":{"a":0,"k":[100,100,100]}},"ao":0,"shapes":[{"ty":"gr","it":[{"ind":0,"ty":"sh","ix":1,"ks":{"a":1,"k":[{"i":{"x":0,"y":1},"o":{"x":1,"y":0},"n":"0_1_1_0","t":501,"s":[{"i":[[0,0],[0,0],[0,0],[0,0]],"o":[[0,0],[0,0],[0,0],[0,0]],"v":[[-109.954,-91.289],[1812.204,-91.289],[1812.204,90.977],[-109.954,90.977]],"c":true}],"e":[{"i":[[0,0],[0,0],[0,0],[0,0]],"o":[[0,0],[0,0],[0,0],[0,0]],"v":[[-109.954,90.461],[1812.204,90.461],[1812.204,649.039],[-109.954,649.039]],"c":true}]},{"t":536.720703125}]},"nm":"Path 1","mn":"ADBE Vector Shape - Group"},{"ty":"fl","c":{"a":0,"k":[0.9843137,0.9882353,0.9921569,1]},"o":{"a":0,"k":100},"r":1,"nm":"Fill 1","mn":"ADBE Vector Graphic - Fill"},{"ty":"tr","p":{"a":0,"k":[-205.454,-449.211],"ix":2},"a":{"a":0,"k":[0,0],"ix":1},"s":{"a":0,"k":[100,100],"ix":3},"r":{"a":0,"k":0,"ix":6},"o":{"a":0,"k":100,"ix":7},"sk":{"a":0,"k":0,"ix":4},"sa":{"a":0,"k":0,"ix":5},"nm":"Transform"}],"nm":"Rectangle 1","np":3,"cix":2,"ix":1,"mn":"ADBE Vector Group"}],"ip":490,"op":549,"st":29,"bm":0,"sr":1},{"ddd":0,"ind":14,"ty":0,"nm":"Testcomp","refId":"comp_1","ks":{"o":{"a":0,"k":100},"r":{"a":0,"k":0},"p":{"a":1,"k":[{"i":{"x":0.667,"y":0.392},"o":{"x":0.333,"y":0},"n":"0p667_0p392_0p333_0","t":14,"s":[3704,540,0],"e":[1432,540,0],"to":[-378.666656494141,0,0],"ti":[862,0,0]},{"i":{"x":0.651,"y":0.629},"o":{"x":0.299,"y":0.439},"n":"0p651_0p629_0p299_0p439","t":234,"s":[1432,540,0],"e":[558.685,540,0],"to":[-375.710540771484,0,0],"ti":[463.973297119141,0,0]},{"i":{"x":0.823,"y":0.65},"o":{"x":0.414,"y":0.342},"n":"0p823_0p65_0p414_0p342","t":302,"s":[558.685,540,0],"e":[-1868,540,0],"to":[-600.529663085938,0,0],"ti":[396.403015136719,0,0]},{"i":{"x":0.366,"y":1},"o":{"x":0.521,"y":0.87},"n":"0p366_1_0p521_0p87","t":449,"s":[-1868,540,0],"e":[-2787,540,0],"to":[-702.666687011719,0,0],"ti":[153.16667175293,0,0]},{"t":496}]},"a":{"a":0,"k":[4705,540,0]},"s":{"a":0,"k":[100,100,100]}},"ao":0,"w":9410,"h":1080,"ip":0,"op":491,"st":0,"bm":0,"sr":1},{"ddd":0,"ind":15,"ty":1,"nm":"Dark Blue Solid 3","ks":{"o":{"a":0,"k":100},"r":{"a":0,"k":0},"p":{"a":0,"k":[960,1080,0]},"a":{"a":0,"k":[960,533,0]},"s":{"a":0,"k":[100,100,100]}},"ao":0,"sw":1920,"sh":533,"sc":"#010138","ip":497,"op":549,"st":29,"bm":0,"sr":1},{"ddd":0,"ind":16,"ty":1,"nm":"Dark Blue Solid 2","ks":{"o":{"a":0,"k":100},"r":{"a":0,"k":0},"p":{"a":0,"k":[960,540,0]},"a":{"a":0,"k":[960,540,0]},"s":{"a":0,"k":[100,100,100]}},"ao":0,"sw":1920,"sh":1080,"sc":"#010138","ip":452,"op":497,"st":29,"bm":0,"sr":1},{"ddd":0,"ind":17,"ty":1,"nm":"White Solid 2","ks":{"o":{"a":0,"k":100},"r":{"a":0,"k":0},"p":{"a":0,"k":[960,540,0]},"a":{"a":0,"k":[960,540,0]},"s":{"a":0,"k":[100,100,100]}},"ao":0,"sw":1920,"sh":1080,"sc":"#f8f8f8","ip":497,"op":660,"st":126,"bm":0,"sr":1}]},{"id":"comp_1","layers":[{"ddd":0,"ind":1,"ty":4,"nm":"Shape Layer 5","td":1,"ks":{"o":{"a":0,"k":100},"r":{"a":0,"k":0},"p":{"a":1,"k":[{"i":{"x":0.896,"y":0.89},"o":{"x":0,"y":0},"n":"0p896_0p89_0_0","t":0,"s":[881.75,449.75,0],"e":[1583.388,449.75,0],"to":[0,0,0],"ti":[-361,0,0]},{"i":{"x":0.498,"y":0.65},"o":{"x":0.588,"y":0.425},"n":"0p498_0p65_0p588_0p425","t":54,"s":[1583.388,449.75,0],"e":[2265.25,809.75,0],"to":[367,27,0],"ti":[-292,4,0]},{"i":{"x":0.667,"y":0.667},"o":{"x":0.333,"y":0.334},"n":"0p667_0p667_0p333_0p334","t":96,"s":[2265.25,809.75,0],"e":[2987.75,809.75,0],"to":[334.843872070312,0,0],"ti":[-26.3441162109375,0,0]},{"i":{"x":0.315,"y":0.448},"o":{"x":0.444,"y":0.356},"n":"0p315_0p448_0p444_0p356","t":151,"s":[2987.75,809.75,0],"e":[3890.25,449.75,0],"to":[304,4,0],"ti":[-568,-1,0]},{"i":{"x":0.667,"y":0.664},"o":{"x":0.333,"y":0.333},"n":"0p667_0p664_0p333_0p333","t":212,"s":[3890.25,449.75,0],"e":[4840.37,449.75,0],"to":[360.999755859375,0,0],"ti":[-360.000244140625,0,0]},{"i":{"x":0.445,"y":0.595},"o":{"x":0.695,"y":0.507},"n":"0p445_0p595_0p695_0p507","t":284,"s":[4840.37,449.75,0],"e":[5511.37,809.75,0],"to":[356,33,0],"ti":[-292,2,0]},{"i":{"x":0.667,"y":0.668},"o":{"x":0.333,"y":0.337},"n":"0p667_0p668_0p333_0p337","t":327,"s":[5511.37,809.75,0],"e":[6050.75,809.75,0],"to":[360,0,0],"ti":[-360,0,0]},{"i":{"x":0.321,"y":0.527},"o":{"x":0.487,"y":0.339},"n":"0p321_0p527_0p487_0p339","t":368,"s":[6050.75,809.75,0],"e":[6952.269,89.75,0],"to":[286,5,0],"ti":[-415,5,0]},{"i":{"x":0.667,"y":0.668},"o":{"x":0.333,"y":0.329},"n":"0p667_0p668_0p333_0p329","t":431.533,"s":[6952.269,89.75,0],"e":[7582.25,89.75,0],"to":[360,0,0],"ti":[0,0,0]},{"t":479}]},"a":{"a":0,"k":[-3014.062,-114.062,0]},"s":{"a":0,"k":[100,100,100]}},"ao":0,"shapes":[{"ty":"gr","it":[{"d":1,"ty":"el","s":{"a":0,"k":[180,180]},"p":{"a":0,"k":[0,0]},"nm":"Ellipse Path 1","mn":"ADBE Vector Shape - Ellipse"},{"ty":"fl","c":{"a":0,"k":[0,0,0,1]},"o":{"a":0,"k":100},"r":1,"nm":"Fill 1","mn":"ADBE Vector Graphic - Fill"},{"ty":"tr","p":{"a":0,"k":[-3014.062,-114.062],"ix":2},"a":{"a":0,"k":[0,0],"ix":1},"s":{"a":1,"k":[{"i":{"x":[0.449,0.449],"y":[1,1]},"o":{"x":[0.575,0.575],"y":[0,0]},"n":["0p449_1_0p575_0","0p449_1_0p575_0"],"t":218,"s":[0,0],"e":[2898,2898]},{"t":274}],"ix":3},"r":{"a":0,"k":0,"ix":6},"o":{"a":1,"k":[{"i":{"x":[0.833],"y":[0.833]},"o":{"x":[0.167],"y":[0.167]},"n":["0p833_0p833_0p167_0p167"],"t":224,"s":[0],"e":[100]},{"t":238}],"ix":7},"sk":{"a":0,"k":0,"ix":4},"sa":{"a":0,"k":0,"ix":5},"nm":"Transform"}],"nm":"Ellipse 1","np":3,"cix":2,"ix":1,"mn":"ADBE Vector Group"}],"ip":0,"op":6000,"st":0,"bm":0,"sr":1},{"ddd":0,"ind":2,"ty":0,"nm":"Outlined värld","tt":1,"refId":"comp_2","ks":{"o":{"a":0,"k":100},"r":{"a":0,"k":0},"p":{"a":0,"k":[4705,540,0]},"a":{"a":0,"k":[4705,540,0]},"s":{"a":0,"k":[100,100,100]}},"ao":0,"w":9410,"h":1080,"ip":0,"op":6000,"st":0,"bm":0,"sr":1},{"ddd":0,"ind":3,"ty":0,"nm":"Solid värld","refId":"comp_3","ks":{"o":{"a":0,"k":100},"r":{"a":0,"k":0},"p":{"a":0,"k":[1001.8,540,0]},"a":{"a":0,"k":[0,540,0]},"s":{"a":0,"k":[100,100,100]}},"ao":0,"w":6488,"h":1080,"ip":0,"op":6000,"st":0,"bm":0,"sr":1}]},{"id":"comp_2","layers":[{"ddd":0,"ind":1,"ty":4,"nm":"Shape Layer 13","ks":{"o":{"a":0,"k":100},"r":{"a":0,"k":0},"p":{"a":0,"k":[7492,90.789,0]},"a":{"a":0,"k":[-315.408,-449.211,0]},"s":{"a":0,"k":[100,100,100]}},"ao":0,"shapes":[{"ty":"gr","it":[{"ind":0,"ty":"sh","ix":1,"ks":{"a":1,"k":[{"i":{"x":0,"y":1},"o":{"x":0.099,"y":0.173},"n":"0_1_0p099_0p173","t":447,"s":[{"i":[[0,0],[0,0],[0,0],[0,0]],"o":[[0,0],[0,0],[0,0],[0,0]],"v":[[-109.954,-91.289],[-104.546,-91.289],[-104.546,91.289],[-109.954,91.289]],"c":true}],"e":[{"i":[[0,0],[0,0],[0,0],[0,0]],"o":[[0,0],[0,0],[0,0],[0,0]],"v":[[-109.954,-91.289],[2688.204,-91.289],[2688.204,92.289],[-109.954,92.289]],"c":true}]},{"t":568}]},"nm":"Path 1","mn":"ADBE Vector Shape - Group"},{"ty":"fl","c":{"a":0,"k":[0.8823529,0.8941176,0.9019608,1]},"o":{"a":0,"k":100},"r":1,"nm":"Fill 1","mn":"ADBE Vector Graphic - Fill"},{"ty":"tr","p":{"a":0,"k":[-205.454,-449.211],"ix":2},"a":{"a":0,"k":[0,0],"ix":1},"s":{"a":0,"k":[100,100],"ix":3},"r":{"a":0,"k":0,"ix":6},"o":{"a":0,"k":100,"ix":7},"sk":{"a":0,"k":0,"ix":4},"sa":{"a":0,"k":0,"ix":5},"nm":"Transform"}],"nm":"Rectangle 1","np":3,"cix":2,"ix":1,"mn":"ADBE Vector Group"}],"ip":447,"op":6001,"st":1,"bm":0,"sr":1},{"ddd":0,"ind":2,"ty":4,"nm":"Shape Layer 12","ks":{"o":{"a":0,"k":100},"r":{"a":0,"k":0},"p":{"a":0,"k":[7492,273.289,0]},"a":{"a":0,"k":[-315.408,-449.211,0]},"s":{"a":0,"k":[100,100,100]}},"ao":0,"shapes":[{"ty":"gr","it":[{"ind":0,"ty":"sh","ix":1,"ks":{"a":1,"k":[{"i":{"x":0,"y":1},"o":{"x":0.107,"y":0.131},"n":"0_1_0p107_0p131","t":453,"s":[{"i":[[0,0],[0,0],[0,0],[0,0]],"o":[[0,0],[0,0],[0,0],[0,0]],"v":[[-109.954,-91.289],[-95.796,-91.289],[-95.796,91.289],[-109.954,91.289]],"c":true}],"e":[{"i":[[0,0],[0,0],[0,0],[0,0]],"o":[[0,0],[0,0],[0,0],[0,0]],"v":[[-109.954,-91.289],[2688.204,-91.289],[2688.204,91.289],[-109.954,91.289]],"c":true}]},{"t":574}]},"nm":"Path 1","mn":"ADBE Vector Shape - Group"},{"ty":"fl","c":{"a":0,"k":[0.9490196,0.9568627,0.9686275,1]},"o":{"a":0,"k":100},"r":1,"nm":"Fill 1","mn":"ADBE Vector Graphic - Fill"},{"ty":"tr","p":{"a":0,"k":[-205.454,-449.211],"ix":2},"a":{"a":0,"k":[0,0],"ix":1},"s":{"a":0,"k":[100,100],"ix":3},"r":{"a":0,"k":0,"ix":6},"o":{"a":0,"k":100,"ix":7},"sk":{"a":0,"k":0,"ix":4},"sa":{"a":0,"k":0,"ix":5},"nm":"Transform"}],"nm":"Rectangle 1","np":3,"cix":2,"ix":1,"mn":"ADBE Vector Group"}],"ip":453,"op":6013,"st":13,"bm":0,"sr":1},{"ddd":0,"ind":3,"ty":4,"nm":"Shape Layer 1","ks":{"o":{"a":0,"k":100},"r":{"a":0,"k":0},"p":{"a":0,"k":[7492,455.289,0]},"a":{"a":0,"k":[-315.408,-449.211,0]},"s":{"a":0,"k":[100,100,100]}},"ao":0,"shapes":[{"ty":"gr","it":[{"ind":0,"ty":"sh","ix":1,"ks":{"a":1,"k":[{"i":{"x":0,"y":1},"o":{"x":0.157,"y":0.273},"n":"0_1_0p157_0p273","t":458,"s":[{"i":[[0,0],[0,0],[0,0],[0,0]],"o":[[0,0],[0,0],[0,0],[0,0]],"v":[[-109.954,-91.289],[-95.14,-91.289],[-95.14,91.289],[-109.954,91.289]],"c":true}],"e":[{"i":[[0,0],[0,0],[0,0],[0,0]],"o":[[0,0],[0,0],[0,0],[0,0]],"v":[[-109.954,-91.289],[2688.86,-91.289],[2688.86,91.289],[-109.954,91.289]],"c":true}]},{"t":578}]},"nm":"Path 1","mn":"ADBE Vector Shape - Group"},{"ty":"fl","c":{"a":0,"k":[0.9843137,0.9882353,0.9921569,1]},"o":{"a":0,"k":100},"r":1,"nm":"Fill 1","mn":"ADBE Vector Graphic - Fill"},{"ty":"tr","p":{"a":0,"k":[-205.454,-449.211],"ix":2},"a":{"a":0,"k":[0,0],"ix":1},"s":{"a":0,"k":[100,100],"ix":3},"r":{"a":0,"k":0,"ix":6},"o":{"a":0,"k":100,"ix":7},"sk":{"a":0,"k":0,"ix":4},"sa":{"a":0,"k":0,"ix":5},"nm":"Transform"}],"nm":"Rectangle 1","np":3,"cix":2,"ix":1,"mn":"ADBE Vector Group"}],"ip":458,"op":6015,"st":15,"bm":0,"sr":1},{"ddd":0,"ind":4,"ty":4,"nm":"Shape Layer 11","ks":{"o":{"a":1,"k":[{"i":{"x":[0.833],"y":[0.833]},"o":{"x":[0.167],"y":[0.167]},"n":["0p833_0p833_0p167_0p167"],"t":482,"s":[100],"e":[0]},{"t":491}]},"r":{"a":0,"k":0},"p":{"a":0,"k":[7492,540.031,0]},"a":{"a":0,"k":[2793,2.031,0]},"s":{"a":0,"k":[100,100,100]}},"ao":0,"shapes":[{"ty":"gr","it":[{"ind":0,"ty":"sh","ix":1,"ks":{"a":0,"k":{"i":[[0,0],[0,0]],"o":[[0,0],[0,0]],"v":[[2793,-538],[2793,542.062]],"c":false}},"nm":"Path 1","mn":"ADBE Vector Shape - Group"},{"ty":"st","c":{"a":0,"k":[0.1137255,0,0.7137255,1]},"o":{"a":0,"k":100},"w":{"a":0,"k":2},"lc":1,"lj":1,"ml":4,"nm":"Stroke 1","mn":"ADBE Vector Graphic - Stroke"},{"ty":"tr","p":{"a":0,"k":[0,0],"ix":2},"a":{"a":0,"k":[0,0],"ix":1},"s":{"a":0,"k":[100,100],"ix":3},"r":{"a":0,"k":0,"ix":6},"o":{"a":0,"k":100,"ix":7},"sk":{"a":0,"k":0,"ix":4},"sa":{"a":0,"k":0,"ix":5},"nm":"Transform"}],"nm":"Shape 1","np":2,"cix":2,"ix":1,"mn":"ADBE Vector Group"}],"ip":0,"op":6000,"st":0,"bm":0,"sr":1},{"ddd":0,"ind":5,"ty":1,"nm":"Black Solid 1","td":1,"ks":{"o":{"a":0,"k":100},"r":{"a":0,"k":0},"p":{"a":0,"k":[7492,540.031,0]},"a":{"a":0,"k":[0,540,0]},"s":{"a":0,"k":[21.275,100,100]}},"ao":0,"sw":9410,"sh":1080,"sc":"#000000","ip":0,"op":6000,"st":0,"bm":0,"sr":1},{"ddd":0,"ind":6,"ty":4,"nm":"Shape Layer 10","tt":2,"ks":{"o":{"a":0,"k":100},"r":{"a":0,"k":0},"p":{"a":1,"k":[{"i":{"x":0.833,"y":1},"o":{"x":0.333,"y":0.405},"n":"0p833_1_0p333_0p405","t":219,"s":[3734.977,99,0],"e":[3874.977,99,0],"to":[3.33333325386047,0,0],"ti":[0,0,0]},{"i":{"x":0.667,"y":0.593},"o":{"x":0.333,"y":0.407},"n":"0p667_0p593_0p333_0p407","t":232,"s":[3874.977,99,0],"e":[4250.35,99,0],"to":[315.27490234375,0,0],"ti":[-272.791015625,0,0]},{"i":{"x":0.316,"y":0.488},"o":{"x":0.463,"y":0.347},"n":"0p316_0p488_0p463_0p347","t":267,"s":[4250.35,99,0],"e":[4971.85,279,0],"to":[370,-1.5,0],"ti":[-340.5,-0.5,0]},{"i":{"x":0.631,"y":0.616},"o":{"x":0.333,"y":0.347},"n":"0p631_0p616_0p333_0p347","t":310,"s":[4971.85,279,0],"e":[5151.523,279,0],"to":[0,0,0],"ti":[-1,0,0]},{"i":{"x":0.434,"y":0.558},"o":{"x":0.576,"y":0.45},"n":"0p434_0p558_0p576_0p45","t":324.281,"s":[5151.523,279,0],"e":[5869.186,459,0],"to":[390,-0.5,0],"ti":[-343.500244140625,0.5,0]},{"i":{"x":0.667,"y":0.668},"o":{"x":0.333,"y":0.332},"n":"0p667_0p668_0p333_0p332","t":369,"s":[5869.186,459,0],"e":[6279.979,459,0],"to":[90.97607421875,0,0],"ti":[-171.2451171875,0,0]},{"i":{"x":0.667,"y":0.683},"o":{"x":1,"y":0.603},"n":"0p667_0p683_1_0p603","t":400.271,"s":[6279.979,459,0],"e":[7751.023,459,0],"to":[2.3857421875,0,0],"ti":[0,0,0]},{"t":468}]},"a":{"a":0,"k":[-3014.062,-114.062,0]},"s":{"a":0,"k":[100,100,100]}},"ao":0,"shapes":[{"ty":"gr","it":[{"d":1,"ty":"el","s":{"a":0,"k":[180,180]},"p":{"a":0,"k":[0,0]},"nm":"Ellipse Path 1","mn":"ADBE Vector Shape - Ellipse"},{"ty":"st","c":{"a":0,"k":[1,1,0,1]},"o":{"a":0,"k":100},"w":{"a":0,"k":2},"lc":1,"lj":1,"ml":4,"nm":"Stroke 1","mn":"ADBE Vector Graphic - Stroke"},{"ty":"tr","p":{"a":0,"k":[-3014.062,-114.062],"ix":2},"a":{"a":0,"k":[0,0],"ix":1},"s":{"a":0,"k":[100,100],"ix":3},"r":{"a":0,"k":0,"ix":6},"o":{"a":0,"k":100,"ix":7},"sk":{"a":0,"k":0,"ix":4},"sa":{"a":0,"k":0,"ix":5},"nm":"Transform"}],"nm":"Ellipse 1","np":3,"cix":2,"ix":1,"mn":"ADBE Vector Group"}],"ip":219,"op":6000,"st":0,"bm":0,"sr":1},{"ddd":0,"ind":7,"ty":4,"nm":"Shape Layer 7","ks":{"o":{"a":0,"k":100},"r":{"a":0,"k":0},"p":{"a":0,"k":[7490,371,0]},"a":{"a":0,"k":[2288.023,0,0]},"s":{"a":0,"k":[100,100,100]}},"ao":0,"shapes":[{"ind":0,"ty":"sh","ix":1,"ks":{"a":0,"k":{"i":[[0,0],[-272.791,0],[-360,0],[-360,0],[-360,0],[-171.246,0],[0,0]],"o":[[315.275,0],[361,0],[360,0],[360,0],[90.976,0],[506.385,0],[0,0]],"v":[[-2288.023,-180],[-952.65,-180],[-231.15,0],[-51.477,0],[666.186,180],[1076.979,180],[2288.023,180]],"c":false}},"nm":"Path 1","mn":"ADBE Vector Shape - Group"},{"ty":"st","c":{"a":0,"k":[1,1,0,1]},"o":{"a":0,"k":100},"w":{"a":0,"k":2},"lc":1,"lj":1,"ml":4,"nm":"Stroke 1","mn":"ADBE Vector Graphic - Stroke"}],"ip":0,"op":6000,"st":0,"bm":0,"sr":1},{"ddd":0,"ind":8,"ty":1,"nm":"Black Solid 1","td":1,"ks":{"o":{"a":0,"k":100},"r":{"a":0,"k":0},"p":{"a":0,"k":[7492,540.031,0]},"a":{"a":0,"k":[0,540,0]},"s":{"a":0,"k":[21.275,100,100]}},"ao":0,"sw":9410,"sh":1080,"sc":"#000000","ip":0,"op":6000,"st":0,"bm":0,"sr":1},{"ddd":0,"ind":9,"ty":4,"nm":"Shape Layer 9","tt":2,"ks":{"o":{"a":0,"k":100},"r":{"a":0,"k":0},"p":{"a":1,"k":[{"i":{"x":0.833,"y":0.848},"o":{"x":0.42,"y":0.384},"n":"0p833_0p848_0p42_0p384","t":219,"s":[3251.773,272.5,0],"e":[3391.773,272.5,0],"to":[3.33333325386047,0,0],"ti":[-254.686767578125,0,0]},{"i":{"x":0.733,"y":0.514},"o":{"x":0.42,"y":0.457},"n":"0p733_0p514_0p42_0p457","t":232,"s":[3391.773,272.5,0],"e":[3628.698,341.227,0],"to":[86.9718856811523,0.66390752792358,0],"ti":[-71.9678115844727,-41.2957992553711,0]},{"i":{"x":0.426,"y":0.633},"o":{"x":0.283,"y":0.303},"n":"0p426_0p633_0p283_0p303","t":252.465,"s":[3628.698,341.227,0],"e":[4294.273,812.5,0],"to":[253.233261108398,145.307586669922,0],"ti":[-233.609252929688,-0.77869749069214,0]},{"i":{"x":0.667,"y":0.669},"o":{"x":0.333,"y":0.331},"n":"0p667_0p669_0p333_0p331","t":292.465,"s":[4294.273,812.5,0],"e":[4969.773,812.5,0],"to":[360,0,0],"ti":[-360,0,0]},{"i":{"x":0.406,"y":0.57},"o":{"x":0.343,"y":0.249},"n":"0p406_0p57_0p343_0p249","t":342.998,"s":[4969.773,812.5,0],"e":[6049.773,272.781,0],"to":[310,0,0],"ti":[-395.60009765625,0,0]},{"i":{"x":0.667,"y":0.76},"o":{"x":0.947,"y":0.355},"n":"0p667_0p76_0p947_0p355","t":410.053,"s":[6049.773,272.781,0],"e":[7819.273,272.5,0],"to":[0,0,0],"ti":[0,0,0]},{"t":460}]},"a":{"a":0,"k":[-3014.062,-114.062,0]},"s":{"a":0,"k":[100,100,100]}},"ao":0,"shapes":[{"ty":"gr","it":[{"d":1,"ty":"el","s":{"a":0,"k":[180,180]},"p":{"a":0,"k":[0,0]},"nm":"Ellipse Path 1","mn":"ADBE Vector Shape - Ellipse"},{"ty":"st","c":{"a":0,"k":[1,0,0.4313725,1]},"o":{"a":0,"k":100},"w":{"a":0,"k":2},"lc":1,"lj":1,"ml":4,"nm":"Stroke 1","mn":"ADBE Vector Graphic - Stroke"},{"ty":"tr","p":{"a":0,"k":[-3014.062,-114.062],"ix":2},"a":{"a":0,"k":[0,0],"ix":1},"s":{"a":0,"k":[100,100],"ix":3},"r":{"a":0,"k":0,"ix":6},"o":{"a":0,"k":100,"ix":7},"sk":{"a":0,"k":0,"ix":4},"sa":{"a":0,"k":0,"ix":5},"nm":"Transform"}],"nm":"Ellipse 1","np":3,"cix":2,"ix":1,"mn":"ADBE Vector Group"}],"ip":0,"op":6000,"st":0,"bm":0,"sr":1},{"ddd":0,"ind":10,"ty":4,"nm":"Shape Layer 5","ks":{"o":{"a":0,"k":100},"r":{"a":0,"k":0},"p":{"a":0,"k":[7490,635.75,0]},"a":{"a":0,"k":[2288.023,0,0]},"s":{"a":0,"k":[100,100,100]}},"ao":0,"shapes":[{"ind":0,"ty":"sh","ix":1,"ks":{"a":0,"k":{"i":[[0,0],[-254.687,0],[-360,0],[-360,0],[-364.6,0],[-360.016,0],[0,0]],"o":[[148.855,0],[361,0],[360,0],[360,0],[0,0],[360.005,0],[0,0]],"v":[[-2288.023,-270],[-1809.477,-270],[-906.977,270],[-231.477,270],[848.523,-269.719],[1748.523,-268.354],[2288.023,-270]],"c":false}},"nm":"Path 1","mn":"ADBE Vector Shape - Group"},{"ty":"st","c":{"a":0,"k":[1,0,0.4313725,1]},"o":{"a":0,"k":100},"w":{"a":0,"k":2},"lc":1,"lj":1,"ml":4,"nm":"Stroke 1","mn":"ADBE Vector Graphic - Stroke"}],"ip":0,"op":6000,"st":0,"bm":0,"sr":1},{"ddd":0,"ind":11,"ty":1,"nm":"Black Solid 1","td":1,"ks":{"o":{"a":0,"k":100},"r":{"a":0,"k":0},"p":{"a":0,"k":[7492,540.031,0]},"a":{"a":0,"k":[0,540,0]},"s":{"a":0,"k":[21.275,100,100]}},"ao":0,"sw":9410,"sh":1080,"sc":"#000000","ip":0,"op":6000,"st":0,"bm":0,"sr":1},{"ddd":0,"ind":12,"ty":4,"nm":"Shape Layer 8","tt":2,"ks":{"o":{"a":0,"k":100},"r":{"a":0,"k":0},"p":{"a":1,"k":[{"i":{"x":0.896,"y":0.89},"o":{"x":0,"y":0},"n":"0p896_0p89_0_0","t":0,"s":[881.75,449.75,0],"e":[1583.388,449.75,0],"to":[0,0,0],"ti":[-361,0,0]},{"i":{"x":0.498,"y":0.65},"o":{"x":0.588,"y":0.425},"n":"0p498_0p65_0p588_0p425","t":54,"s":[1583.388,449.75,0],"e":[2265.25,809.75,0],"to":[367,27,0],"ti":[-292,4,0]},{"i":{"x":0.667,"y":0.667},"o":{"x":0.333,"y":0.334},"n":"0p667_0p667_0p333_0p334","t":96,"s":[2265.25,809.75,0],"e":[2987.75,809.75,0],"to":[334.843872070312,0,0],"ti":[-26.3441162109375,0,0]},{"i":{"x":0.315,"y":0.448},"o":{"x":0.444,"y":0.356},"n":"0p315_0p448_0p444_0p356","t":151,"s":[2987.75,809.75,0],"e":[3890.25,449.75,0],"to":[304,4,0],"ti":[-568,-1,0]},{"i":{"x":0.667,"y":0.664},"o":{"x":0.333,"y":0.333},"n":"0p667_0p664_0p333_0p333","t":212,"s":[3890.25,449.75,0],"e":[4840.37,449.75,0],"to":[360.999755859375,0,0],"ti":[-360.000244140625,0,0]},{"i":{"x":0.445,"y":0.595},"o":{"x":0.695,"y":0.507},"n":"0p445_0p595_0p695_0p507","t":284,"s":[4840.37,449.75,0],"e":[5511.37,809.75,0],"to":[356,33,0],"ti":[-292,2,0]},{"i":{"x":0.667,"y":0.668},"o":{"x":0.333,"y":0.337},"n":"0p667_0p668_0p333_0p337","t":327,"s":[5511.37,809.75,0],"e":[6050.75,809.75,0],"to":[360,0,0],"ti":[-360,0,0]},{"i":{"x":0.321,"y":0.527},"o":{"x":0.487,"y":0.339},"n":"0p321_0p527_0p487_0p339","t":368,"s":[6050.75,809.75,0],"e":[6952.269,89.75,0],"to":[286,5,0],"ti":[-415,5,0]},{"i":{"x":0.991,"y":0.985},"o":{"x":1,"y":0.218},"n":"0p991_0p985_1_0p218","t":431.533,"s":[6952.269,89.75,0],"e":[8182.25,89.75,0],"to":[360,0,0],"ti":[0,0,0]},{"t":452}]},"a":{"a":0,"k":[-3014.062,-114.062,0]},"s":{"a":0,"k":[100,100,100]}},"ao":0,"shapes":[{"ty":"gr","it":[{"d":1,"ty":"el","s":{"a":0,"k":[180,180]},"p":{"a":0,"k":[0,0]},"nm":"Ellipse Path 1","mn":"ADBE Vector Shape - Ellipse"},{"ty":"st","c":{"a":0,"k":[0,0.9411765,0.7058824,1]},"o":{"a":0,"k":100},"w":{"a":0,"k":2},"lc":1,"lj":1,"ml":4,"nm":"Stroke 1","mn":"ADBE Vector Graphic - Stroke"},{"ty":"tr","p":{"a":0,"k":[-3014.062,-114.062],"ix":2},"a":{"a":0,"k":[0,0],"ix":1},"s":{"a":0,"k":[100,100],"ix":3},"r":{"a":0,"k":0,"ix":6},"o":{"a":0,"k":100,"ix":7},"sk":{"a":0,"k":0,"ix":4},"sa":{"a":0,"k":0,"ix":5},"nm":"Transform"}],"nm":"Ellipse 1","np":3,"cix":2,"ix":1,"mn":"ADBE Vector Group"}],"ip":0,"op":6000,"st":0,"bm":0,"sr":1},{"ddd":0,"ind":13,"ty":4,"nm":"Shape Layer 6","ks":{"o":{"a":0,"k":100},"r":{"a":0,"k":0},"p":{"a":0,"k":[1001.75,541,0]},"a":{"a":0,"k":[-3244.25,0,0]},"s":{"a":0,"k":[100,100,100]}},"ao":0,"shapes":[{"ind":0,"ty":"sh","ix":1,"ks":{"a":0,"k":{"i":[[0,0],[360,0],[360,0],[360,0],[360,0],[361,0],[361,0],[334.844,0],[361,0],[0,0]],"o":[[0,0],[-360,0],[-360,0],[-360,0],[-360,0],[-542,0],[-26.344,0],[-361,0],[-361,0],[0,0]],"v":[[3244.25,-360],[2706.269,-360],[1804.75,360],[1265.37,360],[545.37,0],[-355.75,0],[-1258.25,360],[-1980.75,360],[-2702.612,0],[-3244.25,0]],"c":false}},"nm":"Path 1","mn":"ADBE Vector Shape - Group"},{"ty":"st","c":{"a":0,"k":[0,0.9411765,0.7058824,1]},"o":{"a":0,"k":100},"w":{"a":0,"k":2},"lc":1,"lj":1,"ml":4,"nm":"Stroke 1","mn":"ADBE Vector Graphic - Stroke"}],"ip":0,"op":6000,"st":0,"bm":0,"sr":1},{"ddd":0,"ind":14,"ty":1,"nm":"Dark Blue Solid 1","ks":{"o":{"a":0,"k":100},"r":{"a":0,"k":0},"p":{"a":0,"k":[0,540,0]},"a":{"a":0,"k":[0,540,0]},"s":{"a":0,"k":[100,100,100]}},"ao":0,"sw":9410,"sh":1080,"sc":"#010138","ip":0,"op":6000,"st":0,"bm":0,"sr":1}]},{"id":"comp_3","layers":[{"ddd":0,"ind":1,"ty":4,"nm":"Shape Layer 5","ks":{"o":{"a":0,"k":100},"r":{"a":0,"k":0},"p":{"a":1,"k":[{"i":{"x":0.896,"y":0.89},"o":{"x":0,"y":0},"n":"0p896_0p89_0_0","t":0,"s":[-120.25,449.75,0],"e":[581.388,449.75,0],"to":[0,0,0],"ti":[-361,0,0]},{"i":{"x":0.498,"y":0.65},"o":{"x":0.588,"y":0.425},"n":"0p498_0p65_0p588_0p425","t":54,"s":[581.388,449.75,0],"e":[1263.25,809.75,0],"to":[367,27,0],"ti":[-292,4,0]},{"i":{"x":0.667,"y":0.667},"o":{"x":0.333,"y":0.334},"n":"0p667_0p667_0p333_0p334","t":96,"s":[1263.25,809.75,0],"e":[1985.75,809.75,0],"to":[334.843872070312,0,0],"ti":[-26.3441162109375,0,0]},{"i":{"x":0.315,"y":0.448},"o":{"x":0.444,"y":0.356},"n":"0p315_0p448_0p444_0p356","t":151,"s":[1985.75,809.75,0],"e":[2888.25,449.75,0],"to":[304,4,0],"ti":[-568,-1,0]},{"i":{"x":0.667,"y":0.664},"o":{"x":0.333,"y":0.333},"n":"0p667_0p664_0p333_0p333","t":212,"s":[2888.25,449.75,0],"e":[3838.37,449.75,0],"to":[360.999755859375,0,0],"ti":[-360.000244140625,0,0]},{"i":{"x":0.445,"y":0.595},"o":{"x":0.695,"y":0.507},"n":"0p445_0p595_0p695_0p507","t":284,"s":[3838.37,449.75,0],"e":[4509.37,809.75,0],"to":[356,33,0],"ti":[-292,2,0]},{"i":{"x":0.667,"y":0.668},"o":{"x":0.333,"y":0.337},"n":"0p667_0p668_0p333_0p337","t":327,"s":[4509.37,809.75,0],"e":[5048.75,809.75,0],"to":[360,0,0],"ti":[-360,0,0]},{"i":{"x":0.321,"y":0.527},"o":{"x":0.487,"y":0.339},"n":"0p321_0p527_0p487_0p339","t":368,"s":[5048.75,809.75,0],"e":[5950.269,89.75,0],"to":[286,5,0],"ti":[-415,5,0]},{"i":{"x":0.667,"y":0.668},"o":{"x":0.333,"y":0.329},"n":"0p667_0p668_0p333_0p329","t":431.533,"s":[5950.269,89.75,0],"e":[6580.25,89.75,0],"to":[360,0,0],"ti":[0,0,0]},{"t":479}]},"a":{"a":0,"k":[-3014.062,-114.062,0]},"s":{"a":0,"k":[100,100,100]}},"ao":0,"shapes":[{"ty":"gr","it":[{"d":1,"ty":"el","s":{"a":0,"k":[180,180]},"p":{"a":0,"k":[0,0]},"nm":"Ellipse Path 1","mn":"ADBE Vector Shape - Ellipse"},{"ty":"fl","c":{"a":0,"k":[0.1137255,0,0.7137255,1]},"o":{"a":0,"k":100},"r":1,"nm":"Fill 1","mn":"ADBE Vector Graphic - Fill"},{"ty":"tr","p":{"a":0,"k":[-3014.062,-114.062],"ix":2},"a":{"a":0,"k":[0,0],"ix":1},"s":{"a":0,"k":[100,100],"ix":3},"r":{"a":0,"k":0,"ix":6},"o":{"a":0,"k":100,"ix":7},"sk":{"a":0,"k":0,"ix":4},"sa":{"a":0,"k":0,"ix":5},"nm":"Transform"}],"nm":"Ellipse 1","np":3,"cix":2,"ix":1,"mn":"ADBE Vector Group"}],"ip":0,"op":6000,"st":0,"bm":0,"sr":1},{"ddd":0,"ind":2,"ty":4,"nm":"Shape Layer 7","ks":{"o":{"a":0,"k":100},"r":{"a":0,"k":0},"p":{"a":0,"k":[0,1080,0]},"a":{"a":0,"k":[-3244.25,450,0]},"s":{"a":0,"k":[100,100,100]}},"ao":0,"shapes":[{"ind":0,"ty":"sh","ix":1,"ks":{"a":0,"k":{"i":[[360,0],[360,0],[360,0],[360,0],[361,0],[361,0],[334.844,0],[361,0],[0,0],[0,0],[0,0],[0,0],[0,0]],"o":[[-360,0],[-360,0],[-360,0],[-360,0],[-542,0],[-26.344,0],[-361,0],[-361,0],[0,0],[0,0],[0,0],[0,0],[0,0]],"v":[[2706.269,-450],[1804.75,270],[1265.37,270],[545.37,-90],[-355.75,-90],[-1258.25,270],[-1980.75,270],[-2702.612,-90],[-3244.25,-90],[-3244.25,450],[-1331.796,450],[3244.25,450],[3244.25,-450]],"c":true}},"nm":"Path 1","mn":"ADBE Vector Shape - Group"},{"ty":"fl","c":{"a":0,"k":[0,0.9411765,0.7058824,1]},"o":{"a":0,"k":100},"r":1,"nm":"Fill 1","mn":"ADBE Vector Graphic - Fill"}],"ip":0,"op":6000,"st":0,"bm":0,"sr":1},{"ddd":0,"ind":3,"ty":1,"nm":"White Solid 1","ks":{"o":{"a":0,"k":100},"r":{"a":0,"k":0},"p":{"a":0,"k":[3244,540,0]},"a":{"a":0,"k":[3244,540,0]},"s":{"a":0,"k":[100,100,100]}},"ao":0,"sw":6488,"sh":1080,"sc":"#f8f8f8","ip":0,"op":6000,"st":0,"bm":0,"sr":1}]}],"layers":[{"ddd":0,"ind":1,"ty":0,"nm":"Comp 1","refId":"comp_0","ks":{"o":{"a":0,"k":100},"r":{"a":0,"k":0},"p":{"a":0,"k":[960,540,0]},"a":{"a":0,"k":[960,540,0]},"s":{"a":0,"k":[100,100,100]}},"ao":0,"w":1920,"h":1080,"ip":557,"op":6333.62,"st":-26.38,"bm":0,"sr":1.06},{"ddd":0,"ind":2,"ty":0,"nm":"Comp 1","refId":"comp_0","ks":{"o":{"a":0,"k":100},"r":{"a":0,"k":0},"p":{"a":0,"k":[960,540,0]},"a":{"a":0,"k":[960,540,0]},"s":{"a":0,"k":[100,100,100]}},"ao":0,"w":1920,"h":1080,"ip":489,"op":557.679245283019,"st":-212.822641509434,"bm":0,"sr":1.4},{"ddd":0,"ind":3,"ty":0,"nm":"Comp 1","refId":"comp_0","ks":{"o":{"a":0,"k":100},"r":{"a":0,"k":0},"p":{"a":0,"k":[960,540,0]},"a":{"a":0,"k":[960,540,0]},"s":{"a":0,"k":[100,100,100]}},"ao":0,"w":1920,"h":1080,"ip":194,"op":489,"st":-42.38,"bm":0,"sr":1.06},{"ddd":0,"ind":4,"ty":0,"nm":"Comp 1","refId":"comp_0","ks":{"o":{"a":0,"k":100},"r":{"a":0,"k":0},"p":{"a":0,"k":[960,540,0]},"a":{"a":0,"k":[960,540,0]},"s":{"a":0,"k":[100,100,100]}},"ao":0,"w":1920,"h":1080,"ip":0,"op":194.01,"st":0,"bm":0,"sr":0.87}]}